dict2rel/__about__.py
dict2rel/__init__.py
dict2rel/_errors.py
dict2rel/_ravel.py
dict2rel/_schema.py
dict2rel/_types.py
dict2rel/_unravel.py
dict2rel-0.0.3.dist-info/METADATA
dict2rel-0.0.3.dist-info/WHEEL
dict2rel-0.0.3.dist-info/licenses/LICENSE.txt
dict2rel-0.0.3.dist-info/RECORD
