Metadata-Version: 2.4
Name: dict2rel
Version: 0.0.3
Summary: A library for transforming nested JSON data into relational tables and back
Project-URL: Documentation, https://github.com/BlendingJake/Dict2Rel#readme
Project-URL: Issues, https://github.com/BlendingJake/Dict2Rel/issues
Project-URL: Source, https://github.com/BlendingJake/Dict2Rel
Author-email: Jacob Morris <blendingjake@gmail.com>
License-Expression: MIT
License-File: LICENSE.txt
Classifier: Development Status :: 4 - Beta
Classifier: Programming Language :: Python
Classifier: Programming Language :: Python :: 3.8
Classifier: Programming Language :: Python :: 3.9
Classifier: Programming Language :: Python :: 3.10
Classifier: Programming Language :: Python :: 3.11
Classifier: Programming Language :: Python :: 3.12
Classifier: Programming Language :: Python :: Implementation :: CPython
Classifier: Programming Language :: Python :: Implementation :: PyPy
Requires-Python: >=3.8
